autosar_pdf2txt/__init__.py
autosar_pdf2txt/cli/__init__.py
autosar_pdf2txt/cli/autosar_cli.py
autosar_pdf2txt/cli/extract_tables_cli.py
autosar_pdf2txt/config/__init__.py
autosar_pdf2txt/models/__init__.py
autosar_pdf2txt/models/attributes.py
autosar_pdf2txt/models/base.py
autosar_pdf2txt/models/containers.py
autosar_pdf2txt/models/enums.py
autosar_pdf2txt/models/types.py
autosar_pdf2txt/parser/__init__.py
autosar_pdf2txt/parser/base_parser.py
autosar_pdf2txt/parser/class_parser.py
autosar_pdf2txt/parser/enumeration_parser.py
autosar_pdf2txt/parser/pdf_parser.py
autosar_pdf2txt/parser/primitive_parser.py
autosar_pdf2txt/writer/__init__.py
autosar_pdf2txt/writer/markdown_writer.py
autosar_pdf2txt-0.26.0.dist-info/METADATA
autosar_pdf2txt-0.26.0.dist-info/WHEEL
autosar_pdf2txt-0.26.0.dist-info/entry_points.txt
autosar_pdf2txt-0.26.0.dist-info/top_level.txt
autosar_pdf2txt-0.26.0.dist-info/RECORD
