Metadata-Version: 2.4
Name: autosar-pdf2txt
Version: 0.26.0
Summary: A Python package to extract AUTOSAR model from PDF files to markdown
Home-page: https://github.com/yourusername/pdf2txt
Author: Melodypapa
Author-email: melodypapa@outlook.com
Classifier: Development Status :: 3 - Alpha
Classifier: Intended Audience :: Developers
Classifier: License :: OSI Approved :: MIT License
Classifier: Operating System :: OS Independent
Classifier: Programming Language :: Python :: 3
Classifier: Programming Language :: Python :: 3.7
Classifier: Programming Language :: Python :: 3.8
Classifier: Programming Language :: Python :: 3.9
Classifier: Programming Language :: Python :: 3.10
Classifier: Programming Language :: Python :: 3.11
Requires-Python: >=3.7
Requires-Dist: pdfplumber>=0.10.0
Requires-Dist: PyYAML>=5.4.0
Dynamic: author
Dynamic: author-email
Dynamic: classifier
Dynamic: description
Dynamic: description-content-type
Dynamic: home-page
Dynamic: requires-dist
Dynamic: requires-python
Dynamic: summary
